{
  "id": 17,
  "url": "https://ll.thespacedevs.com/2.0.0/launcher/17/",
  "flight_proven": false,
  "serial_number": "B1007",
  "status": "destroyed",
  "details": "Broke up after sucessful water landing",
  "launcher_config": {
    "id": 14,
    "launch_library_id": 1,
    "url": "https://ll.thespacedevs.com/2.0.0/config/launcher/14/",
    "name": "Falcon 9 v1.1",
    "description": "Falcon 9 v1.1 is a significantly redesigned version of the its predecessor, including a higher payload capacity. This version arranges the engines in a structural form SpaceX calls an Octaweb.",
    "family": "Falcon",
    "full_name": "Falcon 9 v1.1",
    "manufacturer": {
      "id": 121,
      "url": "https://ll.thespacedevs.com/2.0.0/agencies/121/",
      "name": "SpaceX",
      "featured": true,
      "type": "Commercial",
      "country_code": "USA",
      "abbrev": "SpX",
      "description": "Space Exploration Technologies Corp., known as SpaceX, is an American aerospace manufacturer and space transport services company headquartered in Hawthorne, California. It was founded in 2002 by entrepreneur Elon Musk with the goal of reducing space transportation costs and enabling the colonization of Mars. SpaceX has many pads, on the East Coast of the US they own SLC-40 at Cape Canaveral and LC-39A at the Kennedy Space Center for their lower inclination launches. They also own SLC-4E at Vandenberg, California for their high inclination launches. Another site is also being developed at Boca Chica, Texas.",
      "administrator": "CEO: Elon Musk",
      "founding_year": "2002",
      "launchers": "Falcon",
      "spacecraft": "Dragon",
      "launch_library_url": "https://launchlibrary.net/1.4/agency/121",
      "total_launch_count": 114,
      "consecutive_successful_launches": 80,
      "successful_launches": 108,
      "failed_launches": 6,
      "pending_launches": 35,
      "consecutive_successful_landings": 20,
      "successful_landings": 75,
      "failed_landings": 12,
      "attempted_landings": 88,
      "info_url": "http://www.spacex.com/",
      "wiki_url": "http://en.wikipedia.org/wiki/SpaceX",
      "logo_url": "https://spacelaunchnow-prod-east.nyc3.digitaloceanspaces.com/media/logo/spacex_logo_20191121063502.png",
      "image_url": "https://spacelaunchnow-prod-east.nyc3.digitaloceanspaces.com/media/agency_images/spacex_image_20190207032501.jpeg",
      "nation_url": "https://spacelaunchnow-prod-east.nyc3.digitaloceanspaces.com/media/agency_nation/spacex_nation_20190207032501.jpeg"
    },
    "program": [
      {
        "id": 11,
        "url": "https://ll.thespacedevs.com/2.0.0/program/11/",
        "name": "Commercial Resupply Services",
        "description": "Commercial Resupply Services (CRS) are a series of flights awarded by NASA for the delivery of cargo and supplies to the International Space Station.The first CRS contracts were signed in 2008 and awarded $1.6 billion to SpaceX for twelve cargo Dragon and $1.9 billion to Orbital Sciences for eight Cygnus flights, covering deliveries to 2016. The Falcon 9 and Antares rockets were also developed under the CRS program to deliver cargo spacecraft to the ISS.",
        "agencies": [
          {
            "id": 44,
            "url": "https://ll.thespacedevs.com/2.0.0/agencies/44/",
            "name": "National Aeronautics and Space Administration",
            "type": "Government"
          },
          {
            "id": 257,
            "url": "https://ll.thespacedevs.com/2.0.0/agencies/257/",
            "name": "Northrop Grumman Innovation Systems",
            "type": "Commercial"
          },
          {
            "id": 1020,
            "url": "https://ll.thespacedevs.com/2.0.0/agencies/1020/",
            "name": "Sierra Nevada Corporation",
            "type": "Commercial"
          },
          {
            "id": 121,
            "url": "https://ll.thespacedevs.com/2.0.0/agencies/121/",
            "name": "SpaceX",
            "type": "Commercial"
          }
        ],
        "image_url": "https://spacelaunchnow-prod-east.nyc3.digitaloceanspaces.com/media/program_images/commercial2520_program_20201129212219.png",
        "start_date": "2008-12-23T00:00:00Z",
        "end_date": null,
        "info_url": null,
        "wiki_url": "https://en.wikipedia.org/wiki/Commercial_Resupply_Services#Commercial_Resupply_Services"
      }
    ],
    "variant": "v1.1",
    "alias": "",
    "min_stage": 2,
    "max_stage": 2,
    "length": 68.4,
    "diameter": 3.65,
    "maiden_flight": "2013-09-29",
    "launch_mass": 506,
    "leo_capacity": 13150,
    "gto_capacity": 4850,
    "to_thrust": 5883,
    "apogee": 200,
    "vehicle_range": null,
    "image_url": "https://spacelaunchnow-prod-east.nyc3.digitaloceanspaces.com/media/launcher_images/falcon252092520v1.1_image_20190222030927.jpeg",
    "info_url": "http://www.spacex.com/falcon9",
    "wiki_url": "https://en.wikipedia.org/wiki/Falcon_9_v1.1",
    "total_launch_count": 15,
    "consecutive_successful_launches": 1,
    "successful_launches": 14,
    "failed_launches": 1,
    "pending_launches": 0
  },
  "image_url": "https://spacelaunchnow-prod-east.nyc3.digitaloceanspaces.com/media/launcher_core_images/17_image_20190226091117.jpg",
  "successful_landings": 1,
  "attempted_landings": 1,
  "flights": 1,
  "last_launch_date": "2014-07-14T15:15:00Z",
  "first_launch_date": "2014-07-14T15:15:00Z"
}